crewlab/__init__.py
crewlab/cli.py
crewlab/controller.py
crewlab-0.0.1.dist-info/LICENSE
crewlab-0.0.1.dist-info/METADATA
crewlab-0.0.1.dist-info/WHEEL
crewlab-0.0.1.dist-info/entry_points.txt
crewlab-0.0.1.dist-info/top_level.txt
crewlab-0.0.1.dist-info/RECORD
